gsuite_sync/__init__.py
gsuite_sync/__main__.py
gsuite_sync/google.py
gsuite_sync/ise.py
gsuite_sync-0.2.1.dist-info/LICENSE
gsuite_sync-0.2.1.dist-info/METADATA
gsuite_sync-0.2.1.dist-info/WHEEL
gsuite_sync-0.2.1.dist-info/entry_points.txt
gsuite_sync-0.2.1.dist-info/top_level.txt
gsuite_sync-0.2.1.dist-info/RECORD
