Metadata-Version: 2.1
Name: gsuite-sync
Version: 0.2.1
Summary: Sync Chromebook MAC addresses from your GSuite into Cisco ISE
Home-page: https://github.com/PackeTsar/gsuite_sync
Author: John W Kerns
Author-email: jkerns@packetsar.com
License: GNU
Platform: UNKNOWN
License-File: LICENSE
Requires-Dist: future
Requires-Dist: oauth2client
Requires-Dist: google-api-python-client
Requires-Dist: requests
Requires-Dist: google-auth-oauthlib
